ntp_manager/__init__.py
ntp_manager/__main__.py
ntp_manager/gui.py
ntp_manager/local_nhp_utils/ntp_file_reader.py
ntp_manager/models.py
ntp_manager/ntp_melt.py
ntp_manager/pa.py
ntp_manager/utils.py
ntp_manager/web.py
ntp_manager/webapp.py
ntp_manager-1.0.6.dist-info/METADATA
ntp_manager-1.0.6.dist-info/WHEEL
ntp_manager-1.0.6.dist-info/entry_points.txt
ntp_manager-1.0.6.dist-info/RECORD
